boraq/__init__.py
boraq/app.py
boraq/boraq.py
boraq/cli.py
boraq/exceptions.py
boraq/commands/__init__.py
boraq/commands/config.py
boraq/commands/git.py
boraq/commands/install.py
boraq/commands/make.py
boraq/commands/setup.py
boraq/commands/update.py
boraq/commands/utils.py
boraq/config/__init__.py
boraq/config/common_site_config.py
boraq/config/lets_encrypt.py
boraq/config/nginx.py
boraq/config/procfile.py
boraq/config/production_setup.py
boraq/config/redis.py
boraq/config/site_config.py
boraq/config/supervisor.py
boraq/config/systemd.py
boraq/config/templates/502.html
boraq/config/templates/Procfile
boraq/config/templates/boraq_manager_nginx.conf
boraq/config/templates/clairview_sudoers
boraq/config/templates/letsencrypt.cfg
boraq/config/templates/nginx.conf
boraq/config/templates/nginx_default.conf
boraq/config/templates/redis_cache.conf
boraq/config/templates/redis_queue.conf
boraq/config/templates/supervisor.conf
boraq/config/templates/systemd/clairview-boraq-clairview-default-worker.service
boraq/config/templates/systemd/clairview-boraq-clairview-long-worker.service
boraq/config/templates/systemd/clairview-boraq-clairview-schedule.service
boraq/config/templates/systemd/clairview-boraq-clairview-short-worker.service
boraq/config/templates/systemd/clairview-boraq-clairview-web.service
boraq/config/templates/systemd/clairview-boraq-node-socketio.service
boraq/config/templates/systemd/clairview-boraq-redis-cache.service
boraq/config/templates/systemd/clairview-boraq-redis-queue.service
boraq/config/templates/systemd/clairview-boraq-redis.target
boraq/config/templates/systemd/clairview-boraq-web.target
boraq/config/templates/systemd/clairview-boraq-workers.target
boraq/config/templates/systemd/clairview-boraq.target
boraq/patches/__init__.py
boraq/patches/patches.txt
boraq/patches/v5/__init__.py
boraq/patches/v5/fix_backup_cronjob.py
boraq/patches/v5/fix_user_permissions.py
boraq/patches/v5/set_live_reload_config.py
boraq/patches/v5/update_archived_sites.py
clairview_boraq-5.0.4.dist-info/METADATA
clairview_boraq-5.0.4.dist-info/WHEEL
clairview_boraq-5.0.4.dist-info/entry_points.txt
clairview_boraq-5.0.4.dist-info/licenses/LICENSE
clairview_boraq-5.0.4.dist-info/RECORD
