Metadata-Version: 2.1
Name: clairview-boraq
Version: 5.0.4
Summary: CLI to manage Multi-tenant deployments for Clairview apps
Project-URL: Changelog, https://github.com/clairview/boraq/releases
Project-URL: Documentation, https://clairviewframework.com/docs/user/en/boraq
Project-URL: Homepage, https://clairview.io/boraq
Project-URL: Source, https://github.com/clairview/boraq
Author-email: Clairview Technologies Ltd <developers@clairview.io>
License-Expression: GPL-3.0-only
License-File: LICENSE
Classifier: Development Status :: 5 - Production/Stable
Classifier: Environment :: Console
Classifier: License :: OSI Approved :: GNU General Public License v3 (GPLv3)
Classifier: Natural Language :: English
Classifier: Operating System :: MacOS
Classifier: Operating System :: OS Independent
Classifier: Topic :: Software Development :: Build Tools
Classifier: Topic :: Software Development :: User Interfaces
Classifier: Topic :: System :: Installation/Setup
Requires-Python: >=3.8
Requires-Dist: click>=7.0
Requires-Dist: gitpython~=3.1.30
Requires-Dist: honcho
Requires-Dist: jinja2~=3.1.3
Requires-Dist: python-crontab~=2.6.0
Requires-Dist: requests
Requires-Dist: semantic-version~=2.10.0
Requires-Dist: setuptools>40.9.0
Requires-Dist: tomli; python_version < '3.11'
